NsoneObservium/NsoneObservium.py
NsoneObservium/__init__.py
NsoneObservium/_version.py
NsoneObservium-1.0.1b1.dist-info/DESCRIPTION.rst
NsoneObservium-1.0.1b1.dist-info/METADATA
NsoneObservium-1.0.1b1.dist-info/RECORD
NsoneObservium-1.0.1b1.dist-info/WHEEL
NsoneObservium-1.0.1b1.dist-info/metadata.json
NsoneObservium-1.0.1b1.dist-info/top_level.txt
