Metadata-Version: 2.0
Name: NsoneObservium
Version: 1.0.1b1
Summary: A simple python library for the Observium API
Home-page: https://github.com/ns1/ns1-observium
Author: bcavanagh@ns1.com
Author-email: bcavanagh@ns1.com
License: UNKNOWN
Keywords: observium network automation
Platform: UNKNOWN
Classifier: Development Status :: 4 - Beta
Classifier: Intended Audience :: System Administrators
Classifier: Topic :: System :: Networking :: Monitoring
Classifier: License :: OSI Approved :: GNU General Public License v3 or later (GPLv3+)
Classifier: Programming Language :: Python :: 2
Classifier: Programming Language :: Python :: 2.7
Classifier: Programming Language :: Python :: 3
Classifier: Programming Language :: Python :: 3.4
Classifier: Programming Language :: Python :: 3.5
Classifier: Programming Language :: Python :: 3.6
Requires-Dist: requests
Requires-Dist: urllib3
